snowman/__init__.py
snowman/analysis.py
snowman/exceptions.py
snowman/headers.py
snowman/history.py
snowman/info.py
snowman/log.py
snowman/man.py
snowman/profit.py
snowman/session.py
snowman/urls.py
snowman/version.py
snowman-0.2.0.dist-info/DESCRIPTION.rst
snowman-0.2.0.dist-info/METADATA
snowman-0.2.0.dist-info/RECORD
snowman-0.2.0.dist-info/WHEEL
snowman-0.2.0.dist-info/entry_points.txt
snowman-0.2.0.dist-info/metadata.json
snowman-0.2.0.dist-info/top_level.txt
